LICENSE.txt
MANIFEST.in
README.md
setup.py
docs/index.txt
gspread/__init__.py
gspread/client.py
gspread/exceptions.py
gspread/httpsession.py
gspread/models.py
gspread/ns.py
gspread/urls.py
gspread/utils.py
gspread_public.egg-info/PKG-INFO
gspread_public.egg-info/SOURCES.txt
gspread_public.egg-info/dependency_links.txt
gspread_public.egg-info/requires.txt
gspread_public.egg-info/top_level.txt